pipeline2app/common/__init__.py
pipeline2app/common/app.py
pipeline2app/common/helpers.py
pipeline2app/common/tasks/__init__.py
pipeline2app/common/tasks/shell.py
pipeline2app/common/tasks/utils.py
pipeline2app/common/tasks/tests/test_shell.py
pipeline2app/core/__init__.py
pipeline2app/core/_version.py
pipeline2app/core/cli.py
pipeline2app/core/exceptions.py
pipeline2app/core/utils.py
pipeline2app/core/version.py
pipeline2app/core/command/__init__.py
pipeline2app/core/command/base.py
pipeline2app/core/command/components.py
pipeline2app/core/command/entrypoint_opts.py
pipeline2app/core/command/tests/test_deploy_command.py
pipeline2app/core/image/__init__.py
pipeline2app/core/image/app.py
pipeline2app/core/image/base.py
pipeline2app/core/image/components.py
pipeline2app/core/image/metapackage.py
pipeline2app/core/image/tests/test_app.py
pipeline2app/core/image/tests/test_image.py
pipeline2app/core/tests/test_cli.py
pipeline2app/core/tests/test_cli_ext.py
pipeline2app/core/tests/test_licenses.py
pipeline2app/core/tests/test_utils.py
pipeline2app/testing/__init__.py
pipeline2app/testing/licenses.py
pipeline2app/testing/tasks.py
pipeline2app-0.17.2.dist-info/METADATA
pipeline2app-0.17.2.dist-info/WHEEL
pipeline2app-0.17.2.dist-info/entry_points.txt
pipeline2app-0.17.2.dist-info/licenses/AUTHORS
pipeline2app-0.17.2.dist-info/licenses/LICENSE
pipeline2app-0.17.2.dist-info/RECORD
