Metadata-Version: 2.4
Name: pipeline2app
Version: 0.17.2
Summary: Pipeline2App: a tool for quickly turning pipelines into containerised applications (e.g. BIDS Apps or XNAT pipelines)
Project-URL: documentation, https://arcanaframework.github.io/pipeline2app
Project-URL: homepage, https://arcanaframework.github.io/pipeline2app
Project-URL: repository, https://github.com/ArcanaFramework/pipeline2app.git
Author-email: "Thomas G. Close" <tom.g.close@gmail.com>
Maintainer-email: "Thomas G. Close" <tom.g.close@gmail.com>
License: Creative Commons Attribution-NonCommercial-ShareAlike 4.0 International Public License
License-File: AUTHORS
License-File: LICENSE
Keywords: pipeline2app
Classifier: Development Status :: 3 - Alpha
Classifier: Environment :: Console
Classifier: Intended Audience :: Science/Research
Classifier: License :: OSI Approved :: Apache Software License
Classifier: Operating System :: MacOS :: MacOS X
Classifier: Operating System :: POSIX :: Linux
Classifier: Programming Language :: Python :: 3.8
Classifier: Programming Language :: Python :: 3.9
Classifier: Programming Language :: Python :: 3.10
Classifier: Programming Language :: Python :: 3.11
Classifier: Programming Language :: Python :: 3.12
Classifier: Topic :: Scientific/Engineering
Requires-Python: >=3.8
Requires-Dist: attrs>=22.1.0
Requires-Dist: build>=0.9
Requires-Dist: click-option-group>=0.5.5
Requires-Dist: click>=8.1.3
Requires-Dist: deepdiff>=3.3
Requires-Dist: docker>=5.0.2
Requires-Dist: fileformats-extras>=0.2.0
Requires-Dist: fileformats>=0.8.5
Requires-Dist: flit-scm>=1.7.0
Requires-Dist: frametree>=0.11.2
Requires-Dist: hatch-vcs>=0.3.0
Requires-Dist: hatchling>=1.12.2
Requires-Dist: neurodocker>=0.9.4
Requires-Dist: pydra>=0.23.0a0
Requires-Dist: pyyaml>=6.0
Requires-Dist: toml
Requires-Dist: typing-extensions
Provides-Extra: dev
Requires-Dist: black; extra == 'dev'
Requires-Dist: codespell; extra == 'dev'
Requires-Dist: flake8; extra == 'dev'
Requires-Dist: flake8-pyproject; extra == 'dev'
Requires-Dist: pre-commit; extra == 'dev'
Requires-Dist: types-pyyaml; extra == 'dev'
Requires-Dist: types-toml; extra == 'dev'
Provides-Extra: docs
Requires-Dist: docutils>=0.10; extra == 'docs'
Requires-Dist: furo>=2022.2.14.1; extra == 'docs'
Requires-Dist: mock>1.0; extra == 'docs'
Requires-Dist: numpydoc>=0.6.0; extra == 'docs'
Requires-Dist: packaging; extra == 'docs'
Requires-Dist: sphinx-argparse>=0.2.0; extra == 'docs'
Requires-Dist: sphinx-click>=3.1; extra == 'docs'
Requires-Dist: sphinx-togglebutton; extra == 'docs'
Requires-Dist: sphinx>=2.1.2; extra == 'docs'
Provides-Extra: test
Requires-Dist: fileformats-medimage-extras; extra == 'test'
Requires-Dist: pytest-cov>=2.12.1; extra == 'test'
Requires-Dist: pytest-env>=0.6.2; extra == 'test'
Requires-Dist: pytest>=6.2.5; extra == 'test'
